readembedability/__init__.py
readembedability/io.py
readembedability/page.py
readembedability/utils.py
readembedability/data/english.pickle
readembedability/data/stopwords.txt
readembedability/parsers/__init__.py
readembedability/parsers/assets.py
readembedability/parsers/base.py
readembedability/parsers/html.py
readembedability/parsers/meta.py
readembedability/parsers/oembed.py
readembedability/parsers/result.py
readembedability/parsers/text.py
readembedability/parsers/content/__init__.py
readembedability/parsers/content/amp.py
readembedability/parsers/content/lastpass.py
readembedability/parsers/content/newspaper.py
readembedability/parsers/content/readability.py
readembedability/parsers/custom/__init__.py
readembedability/parsers/tests/__init__.py
readembedability/parsers/tests/test_meta.py
readembedability/parsers/tests/test_text.py
readembedability/tests/__init__.py
readembedability/tests/soupkitchen.py
readembedability/tests/test_meta.py
readembedability/tests/test_utils.py
readembedability/tests/utils.py
readembedability-1.6.6.dist-info/DESCRIPTION.rst
readembedability-1.6.6.dist-info/METADATA
readembedability-1.6.6.dist-info/RECORD
readembedability-1.6.6.dist-info/WHEEL
readembedability-1.6.6.dist-info/metadata.json
readembedability-1.6.6.dist-info/top_level.txt
