Metadata-Version: 2.0
Name: readembedability
Version: 1.6.6
Summary: Extract structured data from unstructured web pages.
Home-page: http://github.com/bmuller/readembedability
Author: Brian Muller
Author-email: bamuller@gmail.com
License: MIT
Platform: UNKNOWN
Requires-Dist: lxml (==3.8.0)
Requires-Dist: cssselect (==1.0.1)
Requires-Dist: readability-lxml (==0.6.2)
Requires-Dist: robostrippy (==1.3)
Requires-Dist: pyOpenSSL (==17.2.0)
Requires-Dist: beautifulsoup4 (==4.6.0)
Requires-Dist: nltk (==3.2.4)
Requires-Dist: fastimage (==2.0.0)
Requires-Dist: pytidylib (==0.3.2)
Requires-Dist: newspaper3k (==0.2.2)
Requires-Dist: python-dateutil (==2.6.1)
Requires-Dist: aiohttp (==2.2.5)
